quart_redis/__init__.py
quart_redis-3.0.0.dist-info/LICENSE
quart_redis-3.0.0.dist-info/METADATA
quart_redis-3.0.0.dist-info/WHEEL
quart_redis-3.0.0.dist-info/top_level.txt
quart_redis-3.0.0.dist-info/RECORD
