Metadata-Version: 2.1
Name: quart-redis
Version: 3.0.0
Summary: A easy way of setting up a redis in quart
Author: Leo Spratt
License: MIT
Project-URL: homepage, https://github.com/enchant97/quart-redis
Project-URL: documentation, https://quart-redis.readthedocs.io/en/stable/
Project-URL: repository, https://github.com/enchant97/quart-redis.git
Project-URL: changelog, https://github.com/enchant97/quart-redis/blob/master/CHANGELOG.md
Keywords: quart,asyncio,redis,cache
Classifier: License :: OSI Approved :: MIT License
Classifier: Operating System :: OS Independent
Classifier: Programming Language :: Python :: 3
Classifier: Programming Language :: Python :: 3.11
Classifier: Programming Language :: Python :: 3.12
Classifier: Programming Language :: Python :: Implementation :: CPython
Classifier: Intended Audience :: Developers
Classifier: Environment :: Web Environment
Classifier: Topic :: Internet :: WWW/HTTP :: Dynamic Content
Classifier: Topic :: Software Development :: Libraries :: Python Modules
Requires-Python: >=3.11
License-File: LICENSE
Requires-Dist: quart~=0.20
Requires-Dist: redis<6,>=5.2.1
